<text id="SNBD">
<u n="1" who="S0034" trans="nonoverlap" whoConfidence="high">
<vocal desc="laugh"/>
<w pos="UH" lemma="ah" class="INTERJ" usas="Z4">Ah</w>
<w pos="PPIS1" lemma="i" class="PRON" usas="Z8">I</w>
<w pos="VBM" lemma="be" class="VERB" usas="A3">'m</w>
<w pos="RR" lemma="so" class="ADV" usas="Z5">so</w>
</u>
<u n="2" who="UNKMALE" trans="nonoverlap" whoConfidence="low">
<w pos="FU" lemma="--unclearword" class="UNC" usas="Z99">--UNCLEARWORD</w>
</u>
<u n="3" who="S0034" trans="nonoverlap" whoConfidence="high">
<w pos="PPH1" lemma="it" class="PRON" usas="Z8">it</w>
<w pos="VBZ" lemma="be" class="VERB" usas="A3">'s</w>
<w pos="JJ" lemma="funny" class="ADJ" usas="E4:1">funny</w>
<pause dur="short"/>
<w pos="CS" lemma="when" class="CONJ" usas="Z5">when</w>
<w pos="PPIS2" lemma="we" class="PRON" usas="Z8">we</w>
<w pos="VVD" lemma="move" class="VERB" usas="M2">moved</w>
<w pos="II" lemma="to" class="PREP" usas="Z5">to</w>
<w pos="NP1" lemma="--anonplace" class="SUBST" usas="Z2">--ANONplace</w>
<w pos="PPIS2" lemma="we" class="PRON" usas="Z8">we</w>
<w pos="VVD" lemma="go" class="VERB" usas="M1">went</w>
<w pos="II" lemma="to" class="PREP" usas="Z5">to</w>
<w pos="AT" lemma="the" class="ART" usas="Z5">the</w>
<w pos="NN1" lemma="skate" class="SUBST" usas="K5:1">skate</w>
<w pos="NN1" lemma="park" class="SUBST" usas="M7">park</w>
<pause dur="short"/>
<w pos="AT" lemma="the" class="ART" usas="Z5">the</w>
<w pos="NN2" lemma="kid" class="SUBST" usas="S2">kids</w>
<w pos="VBDR" lemma="be" class="VERB" usas="A3">were</w>
<w pos="RR" lemma="like" class="ADV" usas="Z4">like</w>
<w pos="VBR" lemma="be" class="VERB" usas="A3">Are</w>
<w pos="PPY" lemma="you" class="PRON" usas="Z8">you</w>
<w pos="JJ" lemma="posh" class="ADJ" usas="O4:2">posh</w>
<w pos="CC" lemma="or" class="CONJ" usas="Z5">or</w>
<w pos="PN1" lemma="something" class="PRON" usas="Z8">something</w>
<w pos="YQUE" lemma="PUNC" class="STOP" usas="">?</w>
</u>
<u n="4" who="S0123" trans="nonoverlap" whoConfidence="high">
<vocal desc="laugh"/>
</u>
<u n="5" who="S0034" trans="nonoverlap" whoConfidence="high">
<w pos="PPIS1" lemma="i" class="PRON" usas="Z8">I</w>
<w pos="VD0" lemma="do" class="VERB" usas="Z5">do</w>
<w pos="XX" lemma="not" class="ADV" usas="Z6">n't</w>
<w pos="VVI" lemma="understand" class="VERB" usas="X2:5">understand</w>
<w pos="AT" lemma="the" class="ART" usas="Z5">the</w>
<w pos="NN1" lemma="way" class="SUBST" usas="X4:2">way</w>
<w pos="PPY" lemma="you" class="PRON" usas="Z8">you</w>
<w pos="VV0" lemma="talk" class="VERB" usas="Q2:1">talk</w>
<w pos="RR" lemma="actually" class="ADV" usas="A5:4">actually</w>
<vocal desc="laugh"/>
</u>
<u n="6" who="S0123" trans="nonoverlap" whoConfidence="high">
<vocal desc="laugh"/>
</u>
<u n="7" who="S0034" trans="nonoverlap" whoConfidence="high">
<w pos="PPH1" lemma="it" class="PRON" usas="Z8">it</w>
<w pos="VBDZ" lemma="be" class="VERB" usas="A3">was</w>
<w pos="RG" lemma="so" class="ADV" usas="A13:3">so</w>
<w pos="JJ" lemma="funny" class="ADJ" usas="E4:1">funny</w>
<pause dur="short"/>
<w pos="UH" lemma="ah" class="INTERJ" usas="Z4">ah</w>
</u>
<u n="8" who="S0109" trans="nonoverlap" whoConfidence="high">
<w pos="PPIS1" lemma="i" class="PRON" usas="Z8">I</w>
<w pos="RR" lemma="also" class="ADV" usas="N5">also</w>
<w pos="VM" lemma="can" class="VERB" usas="A7">ca</w>
<w pos="XX" lemma="not" class="ADV" usas="Z6">n't</w>
<w pos="VVI" lemma="tell" class="VERB" usas="Q2:2">tell</w>
<w pos="AT" lemma="the" class="ART" usas="Z5">the</w>
<w pos="NN1" lemma="difference" class="SUBST" usas="A6:1">difference</w>
<w pos="II" lemma="between" class="PREP" usas="Z5">between</w>
<w pos="APPGE" lemma="my" class="PRON" usas="Z8">my</w>
<w pos="NN1" lemma="voice" class="SUBST" usas="Q2:1">voice</w>
<w pos="CC" lemma="and" class="CONJ" usas="Z5">and</w>
<w pos="NP1" lemma="--anonnamef" class="SUBST" usas="Z1">--ANONnameF</w>
<w pos="GE" lemma="'s" class="UNC" usas="Z5">'s</w>
<w pos="NN1" lemma="voice" class="SUBST" usas="Q2:1">voice</w>
<pause dur="short"/>
<w pos="DDQ" lemma="which" class="PRON" usas="Z8">which</w>
<w pos="VBZ" lemma="be" class="VERB" usas="A3">is</w>
</u>
<u n="9" who="S0123" trans="nonoverlap" whoConfidence="high">
<w pos="NP1" lemma="--anonnamef" class="SUBST" usas="Z1">--ANONnameF</w>
<w pos="YQUE" lemma="PUNC" class="STOP" usas="">?</w>
</u>
<u n="10" who="S0109" trans="nonoverlap" whoConfidence="high">
<w pos="NP1" lemma="--anonnamef" class="SUBST" usas="Z1">--ANONnameF</w>
<w pos="UH" lemma="um" class="INTERJ" usas="Z4">um</w>
</u>
<u n="11" who="S0123" trans="nonoverlap" whoConfidence="high">
<w pos="NP1" lemma="--anonnamen" class="SUBST" usas="Z1">--ANONnameN</w>
<w pos="YQUE" lemma="PUNC" class="STOP" usas="">?</w>
</u>
<u n="12" who="S0109" trans="nonoverlap" whoConfidence="high">
<w pos="NP1" lemma="--anonnamef" class="SUBST" usas="Z1">--ANONnameF</w>
</u>
<u n="13" who="S0123" trans="nonoverlap" whoConfidence="high">
<w pos="FU" lemma="--unclearword" class="UNC" usas="Z99">--UNCLEARWORD</w>
<w pos="UH" lemma="no" class="INTERJ" usas="Z4">no</w>
<pause dur="short"/>
<w pos="PPHS1" lemma="she" class="PRON" usas="Z8">she</w>
<w pos="VBZ" lemma="be" class="VERB" usas="Z5">'s</w>
<w pos="RR21" lemma="a" class="ADV" usas="A13:3">a</w>
<w pos="RR22" lemma="lot" class="ADV" usas="A13:3">lot</w>
<w pos="RRR" lemma="higher" class="ADV" usas="N3:7">higher</w>
<w pos="VVN" lemma="pitch" class="VERB" usas="M2">pitched</w>
</u>
<u n="14" who="S0109" trans="overlap" whoConfidence="high">
<w pos="RR" lemma="well" class="ADV" usas="A5:1">well</w>
<pause dur="short"/>
<w pos="UH" lemma="no" class="INTERJ" usas="Z4">no</w>
<w pos="CCB" lemma="but" class="CONJ" usas="Z5">but</w>
<pause dur="short"/>
<w pos="II" lemma="in" class="PREP" usas="Z5">in</w>
<w pos="AT1" lemma="a" class="ART" usas="Z5">a</w>
<w pos="NN1" lemma="group" class="SUBST" usas="S5">group</w>
<w pos="NN1" lemma="conversation" class="SUBST" usas="Q2:1">conversation</w>
<pause dur="short"/>
<w pos="PPIS1" lemma="i" class="PRON" usas="Z8">I</w>
<w pos="CC" lemma="and" class="CONJ" usas="Z5">and</w>
<w pos="UH" lemma="um" class="INTERJ" usas="Z4">um</w>
<w pos="VV0" lemma="try" class="VERB" usas="X8">try</w>
<w pos="CC" lemma="and" class="CONJ" usas="Z5">and</w>
<w pos="VV0" lemma="remember" class="VERB" usas="X2:2">remember</w>
<w pos="DDQ" lemma="what" class="PRON" usas="Z8">what</w>
<w pos="PPIS1" lemma="i" class="PRON" usas="Z8">I</w>
<w pos="VVD" lemma="say" class="VERB" usas="Q2:1">said</w>
<w pos="CC" lemma="and" class="CONJ" usas="Z5">and</w>
<w pos="DDQ" lemma="what" class="PRON" usas="Z8">what</w>
<w pos="PPHS1" lemma="she" class="PRON" usas="Z8">she</w>
<w pos="VVD" lemma="say" class="VERB" usas="Q2:1">said</w>
</u>
<u n="15" who="S0123" trans="nonoverlap" whoConfidence="high">
<w pos="PPHS1" lemma="she" class="PRON" usas="Z8">she</w>
<w pos="VBZ" lemma="be" class="VERB" usas="A3">'s</w>
<w pos="RR31" lemma="a" class="ADV" usas="Z5">a</w>
<trunc>
<w pos="FU" lemma="litt-" class="UNC" usas="Z99">litt-</w>
</trunc>
<pause dur="short"/>
<w pos="PPHS1" lemma="she" class="PRON" usas="Z8">she</w>
<w pos="VBZ" lemma="be" class="VERB" usas="A3">'s</w>
<w pos="RR31" lemma="a" class="ADV" usas="A13:6">a</w>
<w pos="RR32" lemma="little" class="ADV" usas="A13:6">little</w>
<w pos="RR33" lemma="bit" class="ADV" usas="A13:6">bit</w>
<w pos="JJR" lemma="posh" class="ADJ" usas="O4:2">posher</w>
<w pos="RR21" lemma="as" class="ADV" usas="N5">as</w>
<w pos="RR22" lemma="well" class="ADV" usas="N5">well</w>
<pause dur="short"/>
<w pos="UH" lemma="uh" class="INTERJ" usas="Z4">uh</w>
<w pos="PPIS1" lemma="i" class="PRON" usas="Z4">I</w>
<w pos="VV0" lemma="think" class="VERB" usas="Z4">think</w>
<w pos="RR" lemma="anyway" class="ADV" usas="Z4">anyway</w>
<pause dur="short"/>
<w pos="CCB" lemma="but" class="CONJ" usas="Z5">but</w>
<w pos="UH" lemma="yeah" class="INTERJ" usas="Z4">yeah</w>
</u>
<u n="16" who="S0034" trans="nonoverlap" whoConfidence="high">
<w pos="UH" lemma="yeah" class="INTERJ" usas="Z4">yeah</w>
</u>
<u n="17" who="S0123" trans="nonoverlap" whoConfidence="high">
<w pos="PPIS1" lemma="i" class="PRON" usas="Z8">I</w>
<w pos="VD0" lemma="do" class="VERB" usas="Z5">du</w>
<w pos="XX" lemma="n" class="ADV" usas="Z5">n</w>
<w pos="VVI" lemma="no" class="VERB" usas="Z6">no</w>
<pause dur="short"/>
<w pos="RR" lemma="so" class="ADV" usas="Z5">so</w>
<w pos="RT" lemma="now" class="ADV" usas="T1:1:2">now</w>
<w pos="PPY" lemma="you" class="PRON" usas="Z8">you</w>
<w pos="VH0" lemma="have" class="VERB" usas="Z5">'ve</w>
<w pos="VVN" lemma="get" class="VERB" usas="A9">got</w>
<w pos="AT" lemma="the" class="ART" usas="Z5">the</w>
<w pos="NN1" lemma="thing" class="SUBST" usas="O2">thing</w>
<w pos="RP" lemma="on" class="ADV" usas="M6">on</w>
<pause dur="short"/>
<w pos="PPIS1" lemma="i" class="PRON" usas="Z8">I</w>
<w pos="VD0" lemma="do" class="VERB" usas="Z5">do</w>
<w pos="XX" lemma="not" class="ADV" usas="Z6">n't</w>
<w pos="VVI" lemma="know" class="VERB" usas="X2:2">know</w>
<w pos="CSW" lemma="if" class="CONJ" usas="Z7">if</w>
<w pos="PPH1" lemma="it" class="PRON" usas="Z8">it</w>
<w pos="VBZ" lemma="be" class="VERB" usas="A3">is</w>
<w pos="II" lemma="on" class="PREP" usas="Z5">on</w>
</u>
<u n="18" who="S0034" trans="nonoverlap" whoConfidence="high">
<w pos="UH" lemma="yeah" class="INTERJ" usas="Z4">yeah</w>
<pause dur="short"/>
<w pos="PPY" lemma="you" class="PRON" usas="Z8">you</w>
<w pos="RR" lemma="suddenly" class="ADV" usas="N3:8">suddenly</w>
<w pos="VV0" lemma="feel" class="VERB" usas="X7">feel</w>
<w pos="II" lemma="like" class="PREP" usas="X7">like</w>
<w pos="AT" lemma="the" class="ART" usas="Z5">the</w>
<w pos="PPY" lemma="you" class="PRON" usas="Z8">you</w>
<w pos="VV0" lemma="feel" class="VERB" usas="X7">feel</w>
<w pos="II" lemma="like" class="PREP" usas="X7">like</w>
<w pos="AT" lemma="the" class="ART" usas="Z5">the</w>
<w pos="NN1" lemma="conversation" class="SUBST" usas="Q2:1">conversation</w>
<w pos="VBZ" lemma="be" class="VERB" usas="Z5">'s</w>
<w pos="VBG" lemma="be" class="VERB" usas="Z5">being</w>
<w pos="VVN" lemma="suck" class="VERB" usas="B1">sucked</w>
<w pos="RP" lemma="out" class="ADV" usas="B1">out</w>
<w pos="AT" lemma="the" class="ART" usas="Z5">the</w>
<w pos="NN1" lemma="air" class="SUBST" usas="O1:3">air</w>
</u>
<u n="19" who="S0109" trans="overlap" whoConfidence="high">
<w pos="RR" lemma="well" class="ADV" usas="A5:1">well</w>
<w pos="PPH1" lemma="it" class="PRON" usas="Z8">it</w>
<w pos="VM" lemma="will" class="VERB" usas="T1:1:3">will</w>
<w pos="VBI" lemma="be" class="VERB" usas="A3">be</w>
<w pos="JJ" lemma="fun" class="ADJ" usas="E4:1">fun</w>
<pause dur="short"/>
<w pos="PPIS2" lemma="we" class="PRON" usas="Z8">we</w>
<w pos="VM" lemma="will" class="VERB" usas="T1:1:3">'ll</w>
<w pos="VVI" lemma="forget" class="VERB" usas="X2:2">forget</w>
</u>
<u n="20" who="S0034" trans="overlap" whoConfidence="high">
<w pos="DD" lemma="some" class="ADJ" usas="N5">some</w>
<w pos="NN1" lemma="sort" class="SUBST" usas="Z4">sort</w>
<w pos="IO" lemma="of" class="PREP" usas="Z4">of</w>
<w pos="JJ" lemma="conversational" class="ADJ" usas="Q2:1">conversational</w>
<w pos="JJ" lemma="conversational" class="ADJ" usas="Q2:1">conversational</w>
<w pos="NN1" lemma="hoovering" class="SUBST" usas="B4">hoovering</w>
<w pos="NN1" lemma="machine" class="SUBST" usas="B4">machine</w>
<pause dur="short"/>
<w pos="CC" lemma="and" class="CONJ" usas="Z5">and</w>
<w pos="II" lemma="in" class="PREP" usas="A5:2">in</w>
<w pos="NN1" lemma="fact" class="SUBST" usas="A5:2">fact</w>
<w pos="PPH1" lemma="it" class="PRON" usas="Z8">it</w>
<w pos="RR" lemma="probably" class="ADV" usas="A7">probably</w>
<w pos="RR" lemma="just" class="ADV" usas="A14">just</w>
<w pos="VVZ" lemma="suck" class="VERB" usas="B1">sucks</w>
<w pos="RP" lemma="out" class="ADV" usas="B1">out</w>
<w pos="RR" lemma="even" class="ADV" usas="A13:1">even</w>
<w pos="AT" lemma="the" class="ART" usas="Z5">the</w>
<w pos="NN1" lemma="impetus" class="SUBST" usas="A2:2">impetus</w>
<w pos="II" lemma="from" class="PREP" usas="Z5">from</w>
<w pos="NN1" lemma="conversation" class="SUBST" usas="Q2:1">conversation</w>
</u>
<u n="21" who="S0109" trans="nonoverlap" whoConfidence="high">
<w pos="UH" lemma="oh" class="INTERJ" usas="Z4">oh</w>
<w pos="RR" lemma="right" class="ADV" usas="Z4">right</w>
</u>
<u n="22" who="S0034" trans="nonoverlap" whoConfidence="high">
<w pos="CS" lemma="cos" class="CONJ" usas="Z5">Cos</w>
<w pos="PPIS2" lemma="we" class="PRON" usas="Z8">we</w>
<w pos="VBR" lemma="be" class="VERB" usas="A3">'re</w>
<w pos="RR" lemma="suddenly" class="ADV" usas="N3:8">suddenly</w>
<w pos="II" lemma="like" class="PREP" usas="Z5">like</w>
<w pos="DD1" lemma="this" class="ADJ" usas="Z8">This</w>
<w pos="VBZ" lemma="be" class="VERB" usas="Z5">is</w>
<w pos="PPY" lemma="you" class="PRON" usas="Z8">you</w>
<w pos="VVG" lemma="talk" class="VERB" usas="Q2:1">talking</w>
<w pos="NP1" lemma="--anonnamem" class="SUBST" usas="Z1">--ANONnameM</w>
<pause dur="short"/>
<w pos="CS" lemma="while" class="CONJ" usas="Z5">while</w>
<vocal desc="laugh"/>
</u>
<u n="23" who="S0109" trans="nonoverlap" whoConfidence="high">
<w pos="PPY" lemma="you" class="PRON" usas="Z8">you</w>
<w pos="VD0" lemma="do" class="VERB" usas="A1:1:1">do</w>
<w pos="XX" lemma="not" class="ADV" usas="Z6">n't</w>
</u>
<u n="24" who="S0123" trans="nonoverlap" whoConfidence="high">
<w pos="PPY" lemma="you" class="PRON" usas="Z8">you</w>
<w pos="RR" lemma="just" class="ADV" usas="A14">just</w>
<w pos="VV0" lemma="generate" class="VERB" usas="A2:2">generate</w>
<w pos="NN1" lemma="conversation" class="SUBST" usas="Q2:1">conversation</w>
<w pos="II" lemma="by" class="PREP" usas="S5">by</w>
<w pos="PPX1" lemma="yourself" class="PRON" usas="S5">yourself</w>
<vocal desc="laugh"/>
</u>
<u n="25" who="S0034" trans="nonoverlap" whoConfidence="high">
<vocal desc="laugh"/>
<w pos="FU" lemma="--unclearword" class="UNC" usas="Z99">--UNCLEARWORD</w>
</u>
<u n="26" who="S0123" trans="nonoverlap" whoConfidence="high">
<w pos="AT" lemma="the" class="ART" usas="Z5">the</w>
<w pos="JJ" lemma="anti-" class="ADJ" usas="A6:1">Anti-</w>
<w pos="NP1" lemma="--anonnamem" class="SUBST" usas="Z1">--ANONnameM</w>
<pause dur="short"/>
<w pos="VVN" lemma="get" class="VERB" usas="A9">got</w>
<w pos="TO" lemma="to" class="PREP" usas="Z3">ta</w>
<w pos="VVI" lemma="wait" class="VERB" usas="T1:3">wait</w>
<w pos="CS" lemma="till" class="CONJ" usas="Z5">till</w>
<w pos="PPY" lemma="you" class="PRON" usas="Z8">you</w>
<w pos="VV0" lemma="go" class="VERB" usas="M1">go</w>
<w pos="VVN" lemma="leave" class="VERB" usas="M1">left</w>
<w pos="RL" lemma="here" class="ADV" usas="M6">here</w>
</u>
<u n="27" who="S0034" trans="nonoverlap" whoConfidence="high">
<w pos="UH" lemma="yeah" class="INTERJ" usas="Z4">yeah</w>
</u>
<u n="28" who="S0123" trans="nonoverlap" whoConfidence="high">
<w pos="NN1" lemma="mirror" class="SUBST" usas="O2">mirror</w>
<w pos="NN1" lemma="signal" class="SUBST" usas="Q1:1">signal</w>
<w pos="NN1" lemma="manoeuvre" class="SUBST" usas="M1">manoeuvre</w>
<pause dur="short"/>
</u>
<u n="29" who="S0034" trans="nonoverlap" whoConfidence="high">
<w pos="UH" lemma="mm" class="INTERJ" usas="Z4">mm</w>
<pause dur="short"/>
<w pos="RR" lemma="definitely" class="ADV" usas="A7">definitely</w>
<pause dur="short"/>
<w pos="RR" lemma="like" class="ADV" usas="Z4">like</w>
<w pos="RG" lemma="very" class="ADV" usas="A13:3">very</w>
<w pos="DA1" lemma="much" class="ADJ" usas="A13:3">much</w>
<pause dur="short"/>
<w pos="FU" lemma="--unclearword" class="UNC" usas="Z99">--UNCLEARWORD</w>
</u>
<u n="30" who="S0123" trans="nonoverlap" whoConfidence="high">
<w pos="UH" lemma="aah" class="INTERJ" usas="Z4">aah</w>
</u>
<u n="31" who="S0034" trans="nonoverlap" whoConfidence="high">
<w pos="VV0" lemma="move" class="VERB" usas="M2">move</w>
<w pos="PN1" lemma="something" class="PRON" usas="Z8">something</w>
<w pos="II" lemma="out" class="PREP" usas="Z5">out</w>
<w pos="AT" lemma="the" class="ART" usas="Z5">the</w>
<w pos="NN1" lemma="way" class="SUBST" usas="X4:2">way</w>
<pause dur="short"/>
<w pos="PPY" lemma="you" class="PRON" usas="Z8">you</w>
<w pos="VBR" lemma="be" class="VERB" usas="A3">'re</w>
<w pos="JJR" lemma="big" class="ADJ" usas="N3:2">bigger</w>
<w pos="CSN" lemma="than" class="CONJ" usas="Z5">than</w>
<w pos="PPHO1" lemma="he" class="PRON" usas="Z8">him</w>
</u>
<u n="32" who="S0123" trans="nonoverlap" whoConfidence="high">
<trunc>
<w pos="FU" lemma="bo-" class="UNC" usas="Z99">Bo-</w>
</trunc>
</u>
<u n="33" who="S0034" trans="nonoverlap" whoConfidence="high">
<w pos="NN1" lemma="survival" class="SUBST" usas="A3">survival</w>
<w pos="IO" lemma="of" class="PREP" usas="Z5">of</w>
<w pos="AT" lemma="the" class="ART" usas="Z5">the</w>
<w pos="JJT" lemma="fit" class="ADJ" usas="A1:2">fittest</w>
<pause dur="short"/>
<w pos="PPH1" lemma="it" class="PRON" usas="Z8">it</w>
<w pos="VBZ" lemma="be" class="VERB" usas="A3">'s</w>
<w pos="AT1" lemma="a" class="ART" usas="Z5">a</w>
<w pos="NN1" lemma="learner" class="SUBST" usas="P1">learner</w>
<w pos="RR" lemma="anyway" class="ADV" usas="Z4">anyway</w>
<pause dur="short"/>
<w pos="PPY" lemma="you" class="PRON" usas="Z8">you</w>
<w pos="VM" lemma="can" class="VERB" usas="A7">can</w>
<w pos="RR" lemma="just" class="ADV" usas="A14">just</w>
<w pos="VVI" lemma="blame" class="VERB" usas="Q2:2">blame</w>
<w pos="PPH1" lemma="it" class="PRON" usas="Z8">it</w>
<w pos="II" lemma="on" class="PREP" usas="Z5">on</w>
<w pos="PPHO1" lemma="he" class="PRON" usas="Z8">him</w>
<pause dur="short"/>
<w pos="PPY" lemma="you" class="PRON" usas="Z8">you</w>
<w pos="VM" lemma="would" class="VERB" usas="A7">'d</w>
<w pos="VBI" lemma="be" class="VERB" usas="A3">be</w>
<w pos="RR" lemma="like" class="ADV" usas="Z4">like</w>
<w pos="UH" lemma="uh" class="INTERJ" usas="Z4">uh</w>
<w pos="FU" lemma="--unclearword" class="UNC" usas="Z99">--UNCLEARWORD</w>
<w pos="NN1" lemma="drive" class="SUBST" usas="M3">drive</w>
<w pos="II" lemma="into" class="PREP" usas="Z5">into</w>
<w pos="DD1" lemma="this" class="ADJ" usas="Z8">this</w>
<w pos="PN1" lemma="one" class="PRON" usas="Z8">one</w>
</u>
<pause dur="long"/>
<u n="34" who="S0123" trans="nonoverlap" whoConfidence="high">
<w pos="JJ" lemma="cool" class="ADJ" usas="O4:6">cool</w>
</u>
<u n="35" who="S0034" trans="nonoverlap" whoConfidence="high">
<w pos="VH0" lemma="have" class="VERB" usas="A9">have</w>
<w pos="PPHS2" lemma="they" class="PRON" usas="Z8">they</w>
<w pos="DB2" lemma="both" class="ADJ" usas="N5">both</w>
<w pos="VVN" lemma="go" class="VERB" usas="M1">gone</w>
<w pos="YQUE" lemma="PUNC" class="STOP" usas="">?</w>
<w pos="UH" lemma="ah" class="INTERJ" usas="Z4">Ah</w>
<pause dur="short"/>
<w pos="DD1" lemma="that" class="ADJ" usas="Z8">that</w>
<w pos="VBZ" lemma="be" class="VERB" usas="A3">'s</w>
<w pos="PPGE" lemma="mine" class="PRON" usas="Z8">mine</w>
</u>
<u n="36" who="S0109" trans="nonoverlap" whoConfidence="high">
<vocal desc="laugh"/>
</u>
<u n="37" who="S0123" trans="overlap" whoConfidence="high">
<vocal desc="laugh"/>
</u>
<u n="38" who="S0034" trans="nonoverlap" whoConfidence="high">
<w pos="DD1" lemma="that" class="ADJ" usas="Z8">that</w>
<w pos="VBZ" lemma="be" class="VERB" usas="A3">'s</w>
<w pos="PPGE" lemma="mine" class="PRON" usas="Z8">mine</w>
</u>
<u n="39" who="S0123" trans="overlap" whoConfidence="high">
<vocal desc="laugh"/>
<w pos="PPY" lemma="you" class="PRON" usas="Z8">You</w>
<vocal desc="laugh"/>
<w pos="PPY" lemma="you" class="PRON" usas="Z8">You</w>
<w pos="VBR" lemma="be" class="VERB" usas="Z5">'re</w>
<w pos="VVN" lemma="beat" class="VERB" usas="X9:2">beaten</w>
<w pos="II" lemma="by" class="PREP" usas="Z5">by</w>
<w pos="AT1" lemma="a" class="ART" usas="Z5">a</w>
<w pos="JJ" lemma="small" class="ADJ" usas="N3:2">small</w>
<w pos="NN1" lemma="car" class="SUBST" usas="M3">car</w>
</u>
<u n="40" who="S0109" trans="overlap" whoConfidence="high">
<w pos="PPH1" lemma="it" class="PRON" usas="Z8">it</w>
<w pos="VBZ" lemma="be" class="VERB" usas="A3">'s</w>
<w pos="JJ" lemma="incredible" class="ADJ" usas="A6:2">incredible</w>
</u>
<u n="41" who="S0034" trans="nonoverlap" whoConfidence="high">
<w pos="UH" lemma="aah" class="INTERJ" usas="Z4">aah</w>
<pause dur="short"/>
<w pos="VV0" lemma="fail" class="VERB" usas="X9:2">fail</w>
<pause dur="short"/>
<w pos="PPGE" lemma="mine" class="PRON" usas="Z8">mine</w>
</u>
<u n="42" who="S0123" trans="nonoverlap" whoConfidence="high">
<w pos="PPY" lemma="you" class="PRON" usas="Z8">you</w>
<w pos="VV0" lemma="need" class="VERB" usas="S6">need</w>
<w pos="TO" lemma="to" class="PREP" usas="Z5">to</w>
<w pos="VVI" lemma="get" class="VERB" usas="A9">get</w>
<w pos="APPGE" lemma="your" class="PRON" usas="Z8">your</w>
<trunc>
<w pos="FU" lemma="s-" class="UNC" usas="Z99">s-</w>
</trunc>
<w pos="JJ" lemma="well" class="ADJ" usas="B2">well</w>
<w pos="CS" lemma="if" class="CONJ" usas="Z7">if</w>
<w pos="PPY" lemma="you" class="PRON" usas="Z8">you</w>
<w pos="VBR" lemma="be" class="VERB" usas="A3">'re</w>
<w pos="NN1" lemma="hand" class="SUBST" usas="B1">hand</w>
<w pos="VBZ" lemma="be" class="VERB" usas="A3">'s</w>
<w pos="RP" lemma="out" class="ADV" usas="M6">out</w>
<w pos="PPY" lemma="you" class="PRON" usas="Z8">you</w>
<w pos="VM" lemma="could" class="VERB" usas="A7">could</w>
<w pos="XX" lemma="not" class="ADV" usas="Z6">n't</w>
<w pos="VVI" lemma="give" class="VERB" usas="A9">give</w>
<w pos="PPIO2" lemma="we" class="PRON" usas="Z8">us</w>
<w pos="AT1" lemma="a" class="ART" usas="Z5">a</w>
<w pos="NN1" lemma="ride" class="SUBST" usas="K5:1">ride</w>
<w pos="VM" lemma="could" class="VERB" usas="A7">could</w>
<w pos="PPY" lemma="you" class="PRON" usas="Z8">you</w>
<w pos="YQUE" lemma="PUNC" class="STOP" usas="">?</w>
</u>
<u n="43" who="S0034" trans="nonoverlap" whoConfidence="high">
<w pos="DDQ" lemma="what" class="PRON" usas="Z8">what</w>
<w pos="VBZ" lemma="be" class="VERB" usas="Z5">is</w>
<w pos="PPH1" lemma="it" class="PRON" usas="Z8">it</w>
<w pos="YQUE" lemma="PUNC" class="STOP" usas="">?</w>
<w pos="AT1" lemma="a" class="ART" usas="Z5">A</w>
<w pos="JJ" lemma="little" class="ADJ" usas="N3:2">little</w>
<w pos="NN1" lemma="lotus" class="SUBST" usas="Z3">Lotus</w>
<w pos="YQUE" lemma="PUNC" class="STOP" usas="">?</w>
<w pos="AT1" lemma="a" class="ART" usas="Z5">A</w>
<w pos="NN1" lemma="lotus" class="SUBST" usas="Z3">Lotus</w>
<w pos="PPIS1" lemma="i" class="PRON" usas="Z8">I</w>
<w pos="VD0" lemma="do" class="VERB" usas="Z5">do</w>
<w pos="XX" lemma="not" class="ADV" usas="Z6">n't</w>
<w pos="VVI" lemma="like" class="VERB" usas="E2">like</w>
<w pos="PPHO2" lemma="they" class="PRON" usas="Z8">them</w>
<w pos="NN2" lemma="thing" class="SUBST" usas="O2">things</w>
</u>
<u n="44" who="S0109" trans="nonoverlap" whoConfidence="high">
<w pos="FU" lemma="--unclearword" class="UNC" usas="Z99">--UNCLEARWORD</w>
</u>
<u n="45" who="S0123" trans="overlap" whoConfidence="high">
<w pos="VV0" lemma="come" class="VERB" usas="M1">come</w>
<w pos="RP" lemma="on" class="ADV" usas="M1">on</w>
<w pos="NP1" lemma="silverstone" class="SUBST" usas="Z2">Silverstone</w>
<pause dur="short"/>
<w pos="PPH1" lemma="it" class="PRON" usas="Z8">it</w>
<w pos="VBZ" lemma="be" class="VERB" usas="A3">'s</w>
<w pos="JJ" lemma="fun" class="ADJ" usas="E4:1">fun</w>
</u>
<u n="46" who="S0123" trans="nonoverlap" whoConfidence="high">
<w pos="NN1" lemma="bit" class="SUBST" usas="N5">bit</w>
<w pos="IO" lemma="of" class="PREP" usas="Z5">of</w>
<w pos="AT1" lemma="a" class="ART" usas="Z5">a</w>
<w pos="UH" lemma="uh" class="INTERJ" usas="Z4">uh</w>
<w pos="NN1" lemma="hairdresser" class="SUBST" usas="B4">hairdresser</w>
<w pos="VBZ" lemma="be" class="VERB" usas="A3">'s</w>
<w pos="PN1" lemma="one" class="PRON" usas="Z8">one</w>
<w pos="RR" lemma="though" class="ADV" usas="Z5">though</w>
<pause dur="short"/>
<w pos="RR" lemma="like" class="ADV" usas="Z4">like</w>
</u>
<u n="47" who="S0109" trans="overlap" whoConfidence="high">
<w pos="PPY" lemma="you" class="PRON" usas="Z8">you</w>
<w pos="VM" lemma="can" class="VERB" usas="A7">ca</w>
<w pos="XX" lemma="not" class="ADV" usas="Z6">n't</w>
<w pos="RR" lemma="really" class="ADV" usas="A5:4">really</w>
<w pos="VVI" lemma="drive" class="VERB" usas="M3">drive</w>
<w pos="RP" lemma="around" class="ADV" usas="M3">around</w>
<w pos="II" lemma="in" class="PREP" usas="Z5">in</w>
<w pos="PPHO2" lemma="they" class="PRON" usas="Z8">them</w>
<w pos="VM" lemma="can" class="VERB" usas="A7">can</w>
<w pos="PPY" lemma="you" class="PRON" usas="Z8">you</w>
<w pos="YQUE" lemma="PUNC" class="STOP" usas="">?</w>
<w pos="AT" lemma="the" class="ART" usas="Z5">The</w>
<w pos="PPHS2" lemma="they" class="PRON" usas="Z8">they</w>
<w pos="VBR" lemma="be" class="VERB" usas="A3">'re</w>
<w pos="PPHS2" lemma="they" class="PRON" usas="Z8">they</w>
<w pos="VBR" lemma="be" class="VERB" usas="A3">are</w>
<w pos="IF" lemma="for" class="PREP" usas="Z5">for</w>
<w pos="VVG" lemma="race" class="VERB" usas="S7:3">racing</w>
<pause dur="short"/>
<w pos="RP" lemma="around" class="ADV" usas="M6">around</w>
<w pos="CCB" lemma="but" class="CONJ" usas="Z5">but</w>
<w pos="XX" lemma="not" class="ADV" usas="Z6">not</w>
</u>
<u n="48" who="S0034" trans="overlap" whoConfidence="high">
<w pos="UH" lemma="mm" class="INTERJ" usas="Z4">mm</w>
</u>
<u n="49" who="S0123" trans="nonoverlap" whoConfidence="high">
<w pos="PPHS2" lemma="they" class="PRON" usas="Z8">they</w>
<w pos="VBR" lemma="be" class="VERB" usas="A3">are</w>
<pause dur="short"/>
<w pos="UH" lemma="yeah" class="INTERJ" usas="Z4">yeah</w>
</u>
<u n="50" who="S0109" trans="overlap" whoConfidence="high">
<w pos="XX" lemma="not" class="ADV" usas="Z6">not</w>
<w pos="VVG" lemma="commute" class="VERB" usas="M3">commuting</w>
</u>
<u n="51" who="S0034" trans="nonoverlap" whoConfidence="high">
<w pos="RR" lemma="well" class="ADV" usas="A5:1">well</w>
<w pos="PPHS2" lemma="they" class="PRON" usas="Z8">they</w>
</u>
<u n="52" who="S0123" trans="nonoverlap" whoConfidence="high">
<w pos="DD1" lemma="that" class="ADJ" usas="Z8">that</w>
<w pos="VBZ" lemma="be" class="VERB" usas="A3">'s</w>
<w pos="DDQ" lemma="what" class="PRON" usas="Z8">what</w>
<w pos="VVZ" lemma="annoy" class="VERB" usas="E3">annoys</w>
<w pos="PPIO1" lemma="i" class="PRON" usas="Z8">me</w>
<w pos="II" lemma="about" class="PREP" usas="Z5">about</w>
<w pos="PPHO2" lemma="they" class="PRON" usas="Z8">them</w>
<w pos="CS" lemma="cos" class="CONJ" usas="Z5">cos</w>
<w pos="PPIS1" lemma="i" class="PRON" usas="Z8">I</w>
<w pos="VV0" lemma="think" class="VERB" usas="X2:1">think</w>
<w pos="PPHS2" lemma="they" class="PRON" usas="Z8">they</w>
<w pos="VBR" lemma="be" class="VERB" usas="A3">'re</w>
<trunc>
<w pos="FU" lemma="coo-" class="UNC" usas="Z99">coo-</w>
</trunc>
<w pos="PPHS2" lemma="they" class="PRON" usas="Z8">they</w>
<w pos="VBR" lemma="be" class="VERB" usas="A3">'re</w>
<w pos="JJ" lemma="cool" class="ADJ" usas="O4:6">cool</w>
<pause dur="short"/>
<w pos="CCB" lemma="but" class="CONJ" usas="Z5">but</w>
<w pos="PPIS1" lemma="i" class="PRON" usas="Z8">I</w>
<w pos="RR" lemma="also" class="ADV" usas="N5">also</w>
<w pos="VV0" lemma="think" class="VERB" usas="X2:1">think</w>
<w pos="CS" lemma="if" class="CONJ" usas="Z7">if</w>
<w pos="PPY" lemma="you" class="PRON" usas="Z8">you</w>
<w pos="VV0" lemma="drive" class="VERB" usas="M3">drive</w>
<w pos="RP" lemma="around" class="ADV" usas="M3">around</w>
<w pos="II" lemma="in" class="PREP" usas="Z5">in</w>
<w pos="PN1" lemma="one" class="PRON" usas="Z8">one</w>
<w pos="PPY" lemma="you" class="PRON" usas="Z8">you</w>
<w pos="VBR" lemma="be" class="VERB" usas="A3">'re</w>
<w pos="AT1" lemma="a" class="ART" usas="A13:6">a</w>
<w pos="NN1" lemma="bit" class="SUBST" usas="A13:6">bit</w>
<w pos="IO" lemma="of" class="PREP" usas="A13:6">of</w>
<w pos="AT1" lemma="a" class="ART" usas="A13:6">a</w>
<w pos="NN1" lemma="jerk" class="SUBST" usas="M2">jerk</w>
<pause dur="short"/>
<w pos="CS" lemma="unless" class="CONJ" usas="Z5">unless</w>
<w pos="PPY" lemma="you" class="PRON" usas="Z8">you</w>
<w pos="VBR" lemma="be" class="VERB" usas="A3">'re</w>
<w pos="AT1" lemma="a" class="ART" usas="Z5">a</w>
<w pos="NN1" lemma="woman" class="SUBST" usas="S2:1">woman</w>
</u>
<u n="53" who="S0034" trans="nonoverlap" whoConfidence="high">
<w pos="UH" lemma="yeah" class="INTERJ" usas="Z4">yeah</w>
<w pos="PPIS1" lemma="i" class="PRON" usas="Z8">I</w>
<w pos="VV0" lemma="know" class="VERB" usas="X2:2">know</w>
<w pos="PPH1" lemma="it" class="PRON" usas="Z8">it</w>
<w pos="VBZ" lemma="be" class="VERB" usas="A3">'s</w>
<w pos="AT1" lemma="a" class="ART" usas="Z5">a</w>
<w pos="NN2" lemma="lady" class="SUBST" usas="S2:1">ladies</w>
<w pos="NN2" lemma="lady" class="SUBST" usas="S2:1">ladies</w>
<w pos="NN1" lemma="wagon" class="SUBST" usas="M3">wagon</w>
</u>
<u n="54" who="S0123" trans="nonoverlap" whoConfidence="high">
<vocal desc="laugh"/>
<w pos="VVN" lemma="manage" class="VERB" usas="S7:1">Managed</w>
<w pos="TO" lemma="to" class="PREP" usas="Z5">to</w>
<w pos="VVI" lemma="get" class="VERB" usas="M1">get</w>
<w pos="RL" lemma="away" class="ADV" usas="M6">away</w>
<w pos="IW" lemma="with" class="PREP" usas="Z5">with</w>
<w pos="DD1" lemma="that" class="ADJ" usas="Z5">that</w>
</u>
<u n="55" who="S0034" trans="nonoverlap" whoConfidence="high">
<w pos="PPIS1" lemma="i" class="PRON" usas="Z8">I</w>
<w pos="UH" lemma="yeah" class="INTERJ" usas="Z4">yeah</w>
<pause dur="short"/>
<w pos="PPIS1" lemma="i" class="PRON" usas="Z8">I</w>
<w pos="VD0" lemma="do" class="VERB" usas="Z8">du</w>
<w pos="XX" lemma="n" class="ADV" usas="Z5">n</w>
<w pos="UH" lemma="no" class="INTERJ" usas="Z4">no</w>
<pause dur="short"/>
<w pos="PPHS2" lemma="they" class="PRON" usas="Z8">they</w>
<w pos="PPHS2" lemma="they" class="PRON" usas="Z8">they</w>
<w pos="PPHS2" lemma="they" class="PRON" usas="Z8">they</w>
<w pos="VV0" lemma="lack" class="VERB" usas="A9">lack</w>
<w pos="AT" lemma="the" class="ART" usas="Z5">the</w>
<w pos="NN1" lemma="kind" class="SUBST" usas="A4:1">kind</w>
<w pos="IO" lemma="of" class="PREP" usas="Z5">of</w>
<pause dur="short"/>
<w pos="PPY" lemma="you" class="PRON" usas="Z4">you</w>
<w pos="VV0" lemma="know" class="VERB" usas="Z4">know</w>
<w pos="PN1" lemma="something" class="PRON" usas="Z8">something</w>
<w pos="II" lemma="about" class="PREP" usas="Z5">about</w>
<w pos="AT" lemma="the" class="ART" usas="Z5">the</w>
<w pos="NP1" lemma="bmw" class="SUBST" usas="Z3">BMW</w>
<w pos="RL" lemma="there" class="ADV" usas="M6">there</w>
<pause dur="short"/>
<w pos="PPH1" lemma="it" class="PRON" usas="Z8">it</w>
<w pos="VHZ" lemma="have" class="VERB" usas="A9">has</w>
<w pos="NN2" lemma="line" class="SUBST" usas="O4:4">lines</w>
<w pos="DDQ" lemma="which" class="PRON" usas="Z8">which</w>
<w pos="VBR" lemma="be" class="VERB" usas="A3">are</w>
<w pos="RR" lemma="just" class="ADV" usas="A14">just</w>
<w pos="PPY" lemma="you" class="PRON" usas="Z4">you</w>
<w pos="VV0" lemma="know" class="VERB" usas="Z4">know</w>
<w pos="JJ" lemma="aggressive" class="ADJ" usas="E3">aggressive</w>
<w pos="CC" lemma="and" class="CONJ" usas="Z5">and</w>
<w pos="JJ" lemma="dangerous" class="ADJ" usas="A15">dangerous</w>
<w pos="CS" lemma="whereas" class="CONJ" usas="Z5">whereas</w>
<w pos="PPIS1" lemma="i" class="PRON" usas="Z8">I</w>
<w pos="VD0" lemma="do" class="VERB" usas="Z5">du</w>
<w pos="XX" lemma="n" class="ADV" usas="Z5">n</w>
<w pos="VVI" lemma="no" class="VERB" usas="Z6">no</w>
<w pos="AT" lemma="the" class="ART" usas="Z5">the</w>
<w pos="NN1" lemma="lotus" class="SUBST" usas="Z3">Lotus</w>
<w pos="VVZ" lemma="look" class="VERB" usas="A6:1">looks</w>
<w pos="II" lemma="like" class="PREP" usas="A6:1">like</w>
<w pos="PPH1" lemma="it" class="PRON" usas="Z8">it</w>
<w pos="VBDZ" lemma="be" class="VERB" usas="Z5">was</w>
<w pos="VVN" lemma="design" class="VERB" usas="C1">designed</w>
<w pos="II" lemma="by" class="PREP" usas="Z5">by</w>
<w pos="DD" lemma="some" class="ADJ" usas="N5">some</w>
<w pos="NN1" lemma="sort" class="SUBST" usas="Z4">sort</w>
<w pos="IO" lemma="of" class="PREP" usas="Z4">of</w>
<w pos="PPY" lemma="you" class="PRON" usas="Z4">you</w>
<w pos="VV0" lemma="know" class="VERB" usas="Z4">know</w>
<w pos="RR" lemma="almost" class="ADV" usas="A13:4">almost</w>
<w pos="II" lemma="like" class="PREP" usas="Z5">like</w>
<w pos="AT1" lemma="a" class="ART" usas="Z5">a</w>
</u>
<u n="56" who="S0123" trans="nonoverlap" whoConfidence="high">
<w pos="UH" lemma="no" class="INTERJ" usas="Z4">no</w>
<w pos="PPH1" lemma="it" class="PRON" usas="Z8">it</w>
<w pos="VBZ" lemma="be" class="VERB" usas="A3">'s</w>
<w pos="JJ" lemma="cool" class="ADJ" usas="O4:6">cool</w>
</u>
<u n="57" who="S0034" trans="nonoverlap" whoConfidence="high">
<w pos="AT1" lemma="a" class="ART" usas="Z5">A</w>
<w pos="AT1" lemma="a" class="ART" usas="Z5">a</w>
<w pos="AT1" lemma="a" class="ART" usas="Z5">a</w>
<w pos="JJ" lemma="talented" class="ADJ" usas="X9:1">talented</w>
<w pos="MC" lemma="three" class="ADJ" usas="N1">three</w>
<w pos="JJ" lemma="year-old" class="ADJ" usas="T3">year-old</w>
</u>
<u n="58" who="S0123" trans="nonoverlap" whoConfidence="high">
<w pos="DDQ" lemma="what" class="PRON" usas="Z8">what</w>
<w pos="YQUE" lemma="PUNC" class="STOP" usas="">?</w>
<w pos="PPH1" lemma="it" class="PRON" usas="Z8">It</w>
<w pos="VBZ" lemma="be" class="VERB" usas="A3">'s</w>
<w pos="RR" lemma="definitely" class="ADV" usas="A7">definitely</w>
<w pos="JJ" lemma="cool" class="ADJ" usas="O4:6">cool</w>
</u>
<u n="59" who="S0109" trans="nonoverlap" whoConfidence="high">
<w pos="CCB" lemma="but" class="CONJ" usas="Z5">but</w>
</u>
<u n="60" who="S0123" trans="nonoverlap" whoConfidence="high">
<w pos="CC" lemma="and" class="CONJ" usas="Z5">and</w>
<w pos="AT" lemma="the" class="ART" usas="Z5">the</w>
<w pos="NP1" lemma="exige" class="SUBST" usas="Z99">Exige</w>
<w pos="RR21" lemma="as" class="ADV" usas="N5">as</w>
<w pos="RR22" lemma="well" class="ADV" usas="N5">well</w>
<w pos="AT" lemma="the" class="ART" usas="Z5">the</w>
<w pos="MD" lemma="next" class="ADJ" usas="N4">next</w>
<w pos="PN1" lemma="one" class="PRON" usas="Z8">one</w>
<w pos="VBZ" lemma="be" class="VERB" usas="A3">is</w>
<w pos="JJ" lemma="cool" class="ADJ" usas="O4:6">cool</w>
<pause dur="short"/>
<w pos="CC" lemma="and" class="CONJ" usas="Z5">and</w>
<w pos="EX" lemma="there" class="PRON" usas="Z5">there</w>
<w pos="VBZ" lemma="be" class="VERB" usas="A3">'s</w>
<w pos="DD1" lemma="another" class="ADJ" usas="A6:1">another</w>
<w pos="PN1" lemma="one" class="PRON" usas="Z8">one</w>
<w pos="II" lemma="after" class="PREP" usas="Z5">after</w>
<w pos="DD1" lemma="that" class="ADJ" usas="Z5">that</w>
<w pos="DDQ" lemma="which" class="PRON" usas="Z8">which</w>
<w pos="VBZ" lemma="be" class="VERB" usas="A3">is</w>
<w pos="RGR" lemma="more" class="ADV" usas="A13:3">more</w>
<w pos="RR21" lemma="sort" class="ADV" usas="Z4">sort</w>
<w pos="RR22" lemma="of" class="ADV" usas="Z4">of</w>
</u>
<u n="61" who="S0034" trans="overlap" whoConfidence="high">
<w pos="UH" lemma="um" class="INTERJ" usas="Z4">um</w>
<pause dur="short"/>
<w pos="PPIS1" lemma="i" class="PRON" usas="Z8">I</w>
<w pos="VV0" lemma="like" class="VERB" usas="E2">like</w>
<w pos="AT" lemma="the" class="ART" usas="Z5">the</w>
<w pos="JJ" lemma="old" class="ADJ" usas="T3">old</w>
<w pos="PPIS1" lemma="i" class="PRON" usas="Z8">I</w>
<w pos="PPIS1" lemma="i" class="PRON" usas="Z8">I</w>
<w pos="VV0" lemma="like" class="VERB" usas="E2">like</w>
<w pos="AT" lemma="the" class="ART" usas="Z5">the</w>
<w pos="JJ" lemma="classic" class="ADJ" usas="A4:1">classic</w>
<w pos="NP1" lemma="bond" class="SUBST" usas="Z1">Bond</w>
<w pos="PN1" lemma="one" class="PRON" usas="Z8">one</w>
<w pos="PPY" lemma="you" class="PRON" usas="Z8">you</w>
<w pos="VV0" lemma="know" class="VERB" usas="X2:2">know</w>
<w pos="AT" lemma="the" class="ART" usas="Z5">the</w>
<w pos="MC2" lemma="eighty" class="ADJ" usas="T1:3">eighties</w>
<w pos="UH" lemma="uh" class="INTERJ" usas="Z4">uh</w>
</u>
<u n="62" who="S0123" trans="nonoverlap" whoConfidence="high">
<w pos="AT" lemma="the" class="ART" usas="Z5">the</w>
<w pos="JJ" lemma="square" class="ADJ" usas="O4:4">square</w>
<w pos="PN1" lemma="one" class="PRON" usas="Z8">one</w>
<pause dur="short"/>
<w pos="CST" lemma="that" class="CONJ" usas="Z8">that</w>
<w pos="VBDZ" lemma="be" class="VERB" usas="A3">was</w>
<w pos="RG" lemma="pretty" class="ADV" usas="A13:5">pretty</w>
<w pos="JJ" lemma="cool" class="ADJ" usas="O4:6">cool</w>
</u>
<u n="63" who="S0034" trans="nonoverlap" whoConfidence="high">
<w pos="AT" lemma="the" class="ART" usas="Z5">the</w>
<w pos="UH" lemma="um" class="INTERJ" usas="Z4">um</w>
</u>
<u n="64" who="S0109" trans="overlap" whoConfidence="high">
<w pos="CCB" lemma="but" class="CONJ" usas="Z5">but</w>
<w pos="NN2" lemma="car" class="SUBST" usas="M3">cars</w>
<w pos="RR" lemma="just" class="ADV" usas="A14">just</w>
<w pos="RR" lemma="generally" class="ADV" usas="A6:2">generally</w>
<w pos="VD0" lemma="do" class="VERB" usas="Z5">do</w>
<w pos="XX" lemma="not" class="ADV" usas="Z6">n't</w>
<w pos="VHI" lemma="have" class="VERB" usas="A9">have</w>
<w pos="NN2" lemma="line" class="SUBST" usas="O4:4">lines</w>
<pause dur="short"/>
<w pos="CC" lemma="and" class="CONJ" usas="Z5">and</w>
<w pos="DD1" lemma="that" class="ADJ" usas="Z8">that</w>
<w pos="VBZ" lemma="be" class="VERB" usas="A3">'s</w>
</u>
<u n="65" who="S0034" trans="nonoverlap" whoConfidence="high">
<w pos="UH" lemma="yeah" class="INTERJ" usas="Z4">yeah</w>
<w pos="PPHS2" lemma="they" class="PRON" usas="Z8">they</w>
<w pos="VD0" lemma="do" class="VERB" usas="A1:1:1">do</w>
</u>
<u n="66" who="S0109" trans="nonoverlap" whoConfidence="high">
<w pos="UH" lemma="no" class="INTERJ" usas="Z4">no</w>
<w pos="VBR" lemma="be" class="VERB" usas="A3">are</w>
<w pos="XX" lemma="not" class="ADV" usas="Z6">n't</w>
<w pos="PPHS2" lemma="they" class="PRON" usas="Z8">they</w>
<w pos="NN2" lemma="curve" class="SUBST" usas="O4:4">curves</w>
<w pos="RT" lemma="nowadays" class="ADV" usas="T1:1:2">nowadays</w>
<w pos="YQUE" lemma="PUNC" class="STOP" usas="">?</w>
</u>
<u n="67" who="S0123" trans="nonoverlap" whoConfidence="high">
<w pos="PPHS2" lemma="they" class="PRON" usas="Z8">they</w>
<w pos="VBR" lemma="be" class="VERB" usas="A3">are</w>
<w pos="UH" lemma="yeah" class="INTERJ" usas="Z4">yeah</w>
</u>
<u n="68" who="S0034" trans="overlap" whoConfidence="high">
<w pos="UH" lemma="yeah" class="INTERJ" usas="Z4">yeah</w>
<w pos="DD1" lemma="that" class="ADJ" usas="Z5">that</w>
<w pos="MC1" lemma="one" class="ADJ" usas="N1">one</w>
<w pos="IO" lemma="of" class="PREP" usas="Z5">of</w>
<w pos="AT" lemma="the" class="ART" usas="Z5">the</w>
<w pos="FU" lemma="--unclearword" class="UNC" usas="Z99">--UNCLEARWORD</w>
<w pos="JJ" lemma="curved" class="ADJ" usas="O4:4">curved</w>
<w pos="CCB" lemma="but" class="CONJ" usas="Z5">but</w>
<w pos="PPIS1" lemma="i" class="PRON" usas="Z4">I</w>
<w pos="VV0" lemma="mean" class="VERB" usas="Z4">mean</w>
<pause dur="short"/>
<w pos="II" lemma="in" class="PREP" usas="Z5">in</w>
<w pos="II" lemma="in" class="PREP" usas="Z5">in</w>
<w pos="NN1" lemma="friendliness" class="SUBST" usas="S1:2:1">friendliness</w>
<w pos="CS" lemma="when" class="CONJ" usas="Z5">when</w>
<w pos="PPHS2" lemma="they" class="PRON" usas="Z8">they</w>
<w pos="CS" lemma="when" class="CONJ" usas="Z5">when</w>
<w pos="CS" lemma="when" class="CONJ" usas="Z5">when</w>
<w pos="AT" lemma="the" class="ART" usas="Z5">the</w>
<w pos="NP1" lemma="ford" class="SUBST" usas="Z1">Ford</w>
<w pos="NP1" lemma="mondeo" class="SUBST" usas="Z1">Mondeo</w>
<w pos="VVD" lemma="come" class="VERB" usas="M1">came</w>
<w pos="II" lemma="in" class="PREP" usas="M1">in</w>
<w pos="PN1" lemma="everyone" class="PRON" usas="Z8">everyone</w>
<w pos="VBDZ" lemma="be" class="VERB" usas="A3">was</w>
<w pos="RR" lemma="like" class="ADV" usas="Z4">like</w>
<w pos="VM21" lemma="let" class="VERB" usas="Z5">Let</w>
<w pos="VM22" lemma="'s" class="VERB" usas="Z5">'s</w>
<w pos="VVI" lemma="make" class="VERB" usas="A1:1:1">make</w>
<w pos="PN1" lemma="everything" class="PRON" usas="Z8">everything</w>
<w pos="VVI" lemma="look" class="VERB" usas="A6:1">look</w>
<w pos="II" lemma="like" class="PREP" usas="A6:1">like</w>
<w pos="AT1" lemma="a" class="ART" usas="Z5">a</w>
<w pos="JJ" lemma="friendly" class="ADJ" usas="S1:2:1">friendly</w>
<w pos="NN1" lemma="smiley" class="SUBST" usas="Q1:2">smiley</w>
<w pos="NN1" lemma="bubble" class="SUBST" usas="O2">bubble</w>
<pause dur="short"/>
</u>
<u n="69" who="S0123" trans="nonoverlap" whoConfidence="high">
<w pos="CC" lemma="and" class="CONJ" usas="Z5">and</w>
<w pos="XX" lemma="not" class="ADV" usas="Z6">not</w>
<w pos="NN1" lemma="kind" class="SUBST" usas="A4:1">kind</w>
<w pos="IO" lemma="of" class="PREP" usas="Z5">of</w>
<w pos="NN2" lemma="remnant" class="SUBST" usas="N5:1">remnants</w>
<w pos="NN1" lemma="thing" class="SUBST" usas="O2">thing</w>
<pause dur="short"/>
<w pos="FU" lemma="--unclearword" class="UNC" usas="Z99">--UNCLEARWORD</w>
</u>
<u n="70" who="S0034" trans="nonoverlap" whoConfidence="high">
<w pos="FU" lemma="--unclearword" class="UNC" usas="Z99">--UNCLEARWORD</w>
<w pos="UH" lemma="um" class="INTERJ" usas="Z4">um</w>
<w pos="MC1" lemma="one" class="ADJ" usas="N1">one</w>
<w pos="FU" lemma="--unclearword" class="UNC" usas="Z99">--UNCLEARWORD</w>
<w pos="NN2" lemma="tree" class="SUBST" usas="L3">trees</w>
</u>
<u n="71" who="S0123" trans="nonoverlap" whoConfidence="high">
<w pos="PPY" lemma="you" class="PRON" usas="Z8">you</w>
<w pos="VM" lemma="should" class="VERB" usas="S6">should</w>
<w pos="RR" lemma="probably" class="ADV" usas="A7">probably</w>
<w pos="VHI" lemma="have" class="VERB" usas="Z5">have</w>
<w pos="RR" lemma="just" class="ADV" usas="A14">just</w>
<w pos="VVN" lemma="go" class="VERB" usas="M1">gone</w>
<w pos="RL" lemma="there" class="ADV" usas="M6">there</w>
<w pos="CC" lemma="and" class="CONJ" usas="Z5">and</w>
<w pos="VVN" lemma="go" class="VERB" usas="M1">gone</w>
<w pos="RP" lemma="over" class="ADV" usas="T2">over</w>
<pause dur="short"/>
<w pos="RR" lemma="like" class="ADV" usas="Z4">like</w>
<w pos="PPHS2" lemma="they" class="PRON" usas="Z8">they</w>
<w pos="VBR" lemma="be" class="VERB" usas="Z5">'re</w>
<w pos="VVG" lemma="go" class="VERB" usas="M1">going</w>
</u>
<u n="72" who="S0034" trans="nonoverlap" whoConfidence="high">
<w pos="NN1" lemma="muh" class="SUBST" usas="Z99">muh</w>
</u>
<u n="73" who="S0109" trans="nonoverlap" whoConfidence="high">
<w pos="PPIS2" lemma="we" class="PRON" usas="Z8">we</w>
<w pos="VD0" lemma="do" class="VERB" usas="Z5">do</w>
<w pos="XX" lemma="not" class="ADV" usas="Z6">n't</w>
<w pos="RR" lemma="actually" class="ADV" usas="A5:4">actually</w>
<w pos="VVI" lemma="need" class="VERB" usas="S6">need</w>
<w pos="TO" lemma="to" class="PREP" usas="Z5">to</w>
<w pos="VBI" lemma="be" class="VERB" usas="A3">be</w>
<w pos="RL" lemma="there" class="ADV" usas="M6">there</w>
<w pos="II" lemma="until" class="PREP" usas="Z5">until</w>
<w pos="NN1" lemma="quarter" class="SUBST" usas="T1:2">quarter</w>
<w pos="II" lemma="to" class="PREP" usas="T1:2">to</w>
<w pos="MC" lemma="eight" class="ADJ" usas="T1:2">eight</w>
</u>
<u n="74" who="S0123" trans="nonoverlap" whoConfidence="high">
<w pos="CS" lemma="until" class="CONJ" usas="Z5">until</w>
<w pos="DDQ" lemma="what" class="PRON" usas="Z8">what</w>
<w pos="YQUE" lemma="PUNC" class="STOP" usas="">?</w>
</u>
<u n="75" who="S0034" trans="overlap" whoConfidence="high">
<w pos="UH" lemma="yeah" class="INTERJ" usas="Z4">yeah</w>
</u>
<u n="76" who="S0123" trans="nonoverlap" whoConfidence="high">
<w pos="II" lemma="until" class="PREP" usas="Z5">until</w>
<w pos="MC" lemma="eight" class="ADJ" usas="N1">eight</w>
<w pos="YQUE" lemma="PUNC" class="STOP" usas="">?</w>
</u>
<u n="77" who="S0109" trans="nonoverlap" whoConfidence="high">
<w pos="NN1" lemma="quarter" class="SUBST" usas="T1:2">quarter</w>
<w pos="II" lemma="to" class="PREP" usas="T1:2">to</w>
<w pos="MC" lemma="eight" class="ADJ" usas="T1:2">eight</w>
</u>
<u n="78" who="S0123" trans="nonoverlap" whoConfidence="high">
<w pos="UH" lemma="yeah" class="INTERJ" usas="Z4">yeah</w>
<w pos="CCB" lemma="but" class="CONJ" usas="Z5">but</w>
<w pos="PPY" lemma="you" class="PRON" usas="Z8">you</w>
<w pos="VVD" lemma="say" class="VERB" usas="Q2:1">said</w>
<w pos="PPH1" lemma="it" class="PRON" usas="Z8">it</w>
<w pos="VBDZ" lemma="be" class="VERB" usas="Z5">was</w>
<w pos="VVGK" lemma="going" class="VERB" usas="T1:1:3">gon</w>
<w pos="TO" lemma="to" class="PREP" usas="Z5">na</w>
<w pos="VVI" lemma="take" class="VERB" usas="A9">take</w>
<w pos="MC" lemma="three" class="ADJ" usas="N1">three</w>
<w pos="NNT2" lemma="hour" class="SUBST" usas="T1:3">hours</w>
</u>
<u n="79" who="S0109" trans="nonoverlap" whoConfidence="high">
<w pos="UH" lemma="no" class="INTERJ" usas="Z4">no</w>
<w pos="PPIS1" lemma="i" class="PRON" usas="Z8">I</w>
<w pos="VDD" lemma="do" class="VERB" usas="A1:1:1">did</w>
<w pos="XX" lemma="not" class="ADV" usas="Z6">n't</w>
<pause dur="short"/>
<w pos="PPIS1" lemma="i" class="PRON" usas="Z8">I</w>
<w pos="VVD" lemma="say" class="VERB" usas="Q2:1">said</w>
<w pos="PPH1" lemma="it" class="PRON" usas="Z8">it</w>
<w pos="VBZ" lemma="be" class="VERB" usas="Z5">'s</w>
<w pos="VVGK" lemma="going" class="VERB" usas="T1:1:3">gon</w>
<w pos="TO" lemma="to" class="PREP" usas="Z5">na</w>
<w pos="VVI" lemma="take" class="VERB" usas="A9">take</w>
<w pos="MC" lemma="two" class="ADJ" usas="N1">two</w>
<w pos="NNT2" lemma="hour" class="SUBST" usas="T1:3">hours</w>
</u>
<u n="80" who="S0123" trans="nonoverlap" whoConfidence="high">
<w pos="PPY" lemma="you" class="PRON" usas="Z8">you</w>
<w pos="VVD" lemma="say" class="VERB" usas="Q2:1">said</w>
<w pos="MC" lemma="two" class="ADJ" usas="N1">two</w>
<w pos="CC" lemma="and" class="CONJ" usas="Z5">and</w>
<w pos="AT1" lemma="a" class="ART" usas="Z5">a</w>
<w pos="NN1" lemma="half" class="SUBST" usas="N5">half</w>
</u>
<u n="81" who="S0109" trans="nonoverlap" whoConfidence="high">
<w pos="PPIS1" lemma="i" class="PRON" usas="Z8">I</w>
<w pos="VVD" lemma="say" class="VERB" usas="Q2:1">said</w>
<w pos="MC" lemma="two" class="ADJ" usas="N1">two</w>
<w pos="PPY" lemma="you" class="PRON" usas="Z8">you</w>
<w pos="VVD" lemma="say" class="VERB" usas="Q2:1">said</w>
<w pos="VM21" lemma="let" class="VERB" usas="Z5">Let</w>
<w pos="VM22" lemma="'s" class="VERB" usas="Z5">'s</w>
<w pos="VVI" lemma="make" class="VERB" usas="X9:2">make</w>
<w pos="PPH1" lemma="it" class="PRON" usas="X9:2">it</w>
<w pos="MC" lemma="two" class="ADJ" usas="N1">two</w>
<w pos="CC" lemma="and" class="CONJ" usas="Z5">and</w>
<w pos="AT1" lemma="a" class="ART" usas="Z5">a</w>
<w pos="NN1" lemma="half" class="SUBST" usas="N5">half</w>
</u>
<u n="82" who="S0123" trans="nonoverlap" whoConfidence="high">
<w pos="UH" lemma="oh" class="INTERJ" usas="Z4">oh</w>
<w pos="RR" lemma="right" class="ADV" usas="Z4">right</w>
<w pos="RR" lemma="okay" class="ADV" usas="A5:1">okay</w>
<pause dur="short"/>
<w pos="CC" lemma="and" class="CONJ" usas="Z5">and</w>
<w pos="RT" lemma="now" class="ADV" usas="T1:1:2">now</w>
<w pos="PPIS1" lemma="i" class="PRON" usas="Z8">I</w>
<w pos="VBM" lemma="be" class="VERB" usas="A3">'m</w>
<w pos="CC" lemma="and" class="CONJ" usas="Z5">and</w>
<w pos="RT" lemma="now" class="ADV" usas="T1:1:2">now</w>
<w pos="PPIS1" lemma="i" class="PRON" usas="Z8">I</w>
<w pos="VBM" lemma="be" class="VERB" usas="Z5">'m</w>
<w pos="VVG" lemma="think" class="VERB" usas="X2:1">thinking</w>
<w pos="PPH1" lemma="it" class="PRON" usas="Z8">it</w>
<w pos="VM" lemma="will" class="VERB" usas="T1:1:3">'ll</w>
<w pos="VBI" lemma="be" class="VERB" usas="A3">be</w>
<w pos="MC" lemma="three" class="ADJ" usas="N1">three</w>
</u>
<u n="83" who="S0034" trans="overlap" whoConfidence="high">
<w pos="DB" lemma="all" class="ADJ" usas="N5:1">all</w>
<w pos="PPY" lemma="you" class="PRON" usas="Z8">you</w>
<pause dur="short"/>
<w pos="VVG" lemma="gamble" class="VERB" usas="A15">gambling</w>
<w pos="RL" lemma="upwards" class="ADV" usas="M6">upwards</w>
<pause dur="short"/>
<w pos="DB" lemma="all" class="ADJ" usas="T2">all</w>
<w pos="AT" lemma="the" class="ART" usas="T2">the</w>
<w pos="NNT1" lemma="time" class="SUBST" usas="T2">time</w>
</u>
<u n="84" who="S0123" trans="nonoverlap" whoConfidence="high">
<vocal desc="laugh"/>
<w pos="NN1" lemma="gambling" class="SUBST" usas="A15">gambling</w>
<w pos="RL" lemma="upwards" class="ADV" usas="M6">upwards</w>
</u>
<u n="85" who="S0109" trans="nonoverlap" whoConfidence="high">
<w pos="PPH1" lemma="it" class="PRON" usas="Z8">it</w>
<w pos="VBZ" lemma="be" class="VERB" usas="A3">'s</w>
<w pos="RRR" lemma="more" class="ADV" usas="A13:3">more</w>
<w pos="AT" lemma="the" class="ART" usas="Z5">the</w>
<w pos="NN1" lemma="point" class="SUBST" usas="Q2:1">point</w>
<w pos="CST" lemma="that" class="CONJ" usas="Z5">that</w>
<w pos="NP1" lemma="becca" class="SUBST" usas="Z1">Becca</w>
<w pos="VBZ" lemma="be" class="VERB" usas="Z5">'s</w>
<w pos="RR" lemma="probably" class="ADV" usas="A7">probably</w>
<w pos="VVG" lemma="sit" class="VERB" usas="M8">sitting</w>
<w pos="RL" lemma="there" class="ADV" usas="M6">there</w>
<w pos="VVG" lemma="go" class="VERB" usas="M1">going</w>
<w pos="DDQ" lemma="what" class="PRON" usas="Z8">What</w>
<w pos="VHZ" lemma="have" class="VERB" usas="Z5">'s</w>
<w pos="VVN" lemma="happen" class="VERB" usas="A2:1">happened</w>
<w pos="YQUE" lemma="PUNC" class="STOP" usas="">?</w>
</u>
<u n="86" who="S0123" trans="overlap" whoConfidence="high">
<w pos="JJ" lemma="sorry" class="ADJ" usas="Z4">sorry</w>
<w pos="DDQ" lemma="what" class="PRON" usas="Z8">what</w>
<w pos="YQUE" lemma="PUNC" class="STOP" usas="">?</w>
<w pos="UH" lemma="no" class="INTERJ" usas="Z4">No</w>
<w pos="CS" lemma="cos" class="CONJ" usas="Z5">cos</w>
<w pos="PPIS2" lemma="we" class="PRON" usas="Z8">we</w>
<w pos="VH0" lemma="have" class="VERB" usas="Z5">'ve</w>
<w pos="VVN" lemma="tell" class="VERB" usas="Q2:1">told</w>
<w pos="PPHO1" lemma="she" class="PRON" usas="Z8">her</w>
<w pos="RR" lemma="already" class="ADV" usas="T1:1:1">already</w>
</u>
<u n="87" who="S0034" trans="nonoverlap" whoConfidence="high">
<w pos="UH" lemma="mm" class="INTERJ" usas="Z4">mm</w>
<pause dur="short"/>
<w pos="PPHS1" lemma="she" class="PRON" usas="Z8">she</w>
<w pos="VBDZ" lemma="be" class="VERB" usas="A3">was</w>
<w pos="JJ" lemma="grateful" class="ADJ" usas="S1:2:4">grateful</w>
<w pos="IF" lemma="for" class="PREP" usas="Z5">for</w>
<w pos="DD1" lemma="that" class="ADJ" usas="Z5">that</w>
<pause dur="short"/>
<w pos="PPIS1" lemma="i" class="PRON" usas="Z8">I</w>
<w pos="VV0" lemma="think" class="VERB" usas="X2:1">think</w>
<w pos="PPHS1" lemma="she" class="PRON" usas="Z8">she</w>
<w pos="VBDZ" lemma="be" class="VERB" usas="Z5">was</w>
<w pos="VVG" lemma="run" class="VERB" usas="M1">running</w>
<w pos="RR21" lemma="a" class="ADV" usas="A13:6">a</w>
<w pos="RR22" lemma="bit" class="ADV" usas="A13:6">bit</w>
<w pos="JJ" lemma="late" class="ADJ" usas="T4">late</w>
</u>
<u n="88" who="S0109" trans="nonoverlap" whoConfidence="high">
<w pos="UH" lemma="mhm" class="INTERJ" usas="Z4">mhm</w>
</u>
<u n="89" who="S0034" trans="nonoverlap" whoConfidence="high">
<w pos="PPIS1" lemma="i" class="PRON" usas="Z8">I</w>
<w pos="VH0" lemma="have" class="VERB" usas="A9">'ve</w>
<pause dur="short"/>
<w pos="UH" lemma="mm" class="INTERJ" usas="Z4">mm</w>
<pause dur="short"/>
<w pos="FU" lemma="--unclearword" class="UNC" usas="Z99">--UNCLEARWORD</w>
<w pos="VVG" lemma="drive" class="VERB" usas="M3">driving</w>
<w pos="DD1" lemma="this" class="ADJ" usas="M6">this</w>
<w pos="NN1" lemma="bastion" class="SUBST" usas="S8">bastion</w>
<w pos="IO" lemma="of" class="PREP" usas="Z5">of</w>
<w pos="NN1" lemma="punctuality" class="SUBST" usas="T4">punctuality</w>
</u>
<u n="90" who="S0123" trans="nonoverlap" whoConfidence="high">
<vocal desc="laugh"/>
<w pos="UH" lemma="yeah" class="INTERJ" usas="Z4">Yeah</w>
</u>
<pause dur="long"/>
<u n="91" who="S0034" trans="nonoverlap" whoConfidence="high">
<w pos="UH" lemma="yeah" class="INTERJ" usas="Z4">yeah</w>
<w pos="PPIS1" lemma="i" class="PRON" usas="Z8">I</w>
<w pos="VV0" lemma="think" class="VERB" usas="X2:1">think</w>
<w pos="PPIS1" lemma="i" class="PRON" usas="Z8">I</w>
<w pos="VM" lemma="would" class="VERB" usas="A7">'d</w>
<w pos="VVI" lemma="take" class="VERB" usas="A9">take</w>
<w pos="AT" lemma="the" class="ART" usas="Z5">the</w>
<w pos="FO" lemma="z4" class="UNC" usas="Z99">Z4</w>
<w pos="II" lemma="over" class="PREP" usas="Z5">over</w>
<w pos="AT" lemma="the" class="ART" usas="Z5">the</w>
<w pos="UH" lemma="uh" class="INTERJ" usas="Z4">uh</w>
<w pos="FU" lemma="--unclearword" class="UNC" usas="Z99">--UNCLEARWORD</w>
</u>
<u n="92" who="S0123" trans="overlap" whoConfidence="high">
<w pos="UH" lemma="uh" class="INTERJ" usas="Z4">uh</w>
<w pos="PPHS2" lemma="they" class="PRON" usas="Z8">they</w>
<w pos="VBR" lemma="be" class="VERB" usas="A3">'re</w>
<w pos="JJ" lemma="ugly" class="ADJ" usas="O4:2">ugly</w>
</u>
<u n="93" who="S0034" trans="overlap" whoConfidence="high">
<w pos="FU" lemma="--unclearword" class="UNC" usas="Z99">--UNCLEARWORD</w>
<w pos="UH" lemma="hm" class="INTERJ" usas="Z4">Hm</w>
<w pos="YQUE" lemma="PUNC" class="STOP" usas="">?</w>
</u>
<u n="94" who="S0123" trans="nonoverlap" whoConfidence="high">
<w pos="UH" lemma="yeah" class="INTERJ" usas="Z4">yeah</w>
<w pos="II21" lemma="apart" class="PREP" usas="A1:8">apart</w>
<w pos="II22" lemma="from" class="PREP" usas="A1:8">from</w>
<w pos="AT" lemma="the" class="ART" usas="Z5">the</w>
<w pos="NN1" lemma="kind" class="SUBST" usas="A4:1">kind</w>
<w pos="IO" lemma="of" class="PREP" usas="Z5">of</w>
<w pos="RR" lemma="really" class="ADV" usas="A13:3">really</w>
<w pos="JJ" lemma="old" class="ADJ" usas="T3">old</w>
<w pos="NN1" lemma="school" class="SUBST" usas="P1">school</w>
<w pos="NN1" lemma="style" class="SUBST" usas="X4:2">style</w>
<w pos="MC1" lemma="one" class="ADJ" usas="N1">one</w>
</u>
<u n="95" who="S0034" trans="nonoverlap" whoConfidence="high">
<w pos="UH" lemma="yep" class="INTERJ" usas="Z4">yep</w>
<pause dur="short"/>
<w pos="RR" lemma="well" class="ADV" usas="A5:1">well</w>
<w pos="CS" lemma="while" class="CONJ" usas="Z5">while</w>
<w pos="PPY" lemma="you" class="PRON" usas="Z8">you</w>
<w pos="VV0" lemma="tank" class="VERB" usas="M3">tank</w>
<w pos="RP" lemma="up" class="ADV" usas="Z5">up</w>
<w pos="PPIS1" lemma="i" class="PRON" usas="Z8">I</w>
<w pos="VBM" lemma="be" class="VERB" usas="Z5">'m</w>
<w pos="VVGK" lemma="going" class="VERB" usas="T1:1:3">gon</w>
<w pos="TO" lemma="to" class="PREP" usas="Z5">na</w>
<w pos="VVI" lemma="get" class="VERB" usas="A9">get</w>
<w pos="PPX1" lemma="myself" class="PRON" usas="Z8">myself</w>
<w pos="AT1" lemma="a" class="ART" usas="Z5">a</w>
<w pos="NN1" lemma="toothbrush" class="SUBST" usas="B4">toothbrush</w>
</u>
<u n="96" who="S0109" trans="nonoverlap" whoConfidence="high">
<w pos="PPY" lemma="you" class="PRON" usas="Z8">you</w>
<w pos="VH0" lemma="have" class="VERB" usas="Z5">'ve</w>
<w pos="VVN" lemma="forget" class="VERB" usas="X2:2">forgotten</w>
<w pos="PN1" lemma="one" class="PRON" usas="Z8">one</w>
<w pos="YQUE" lemma="PUNC" class="STOP" usas="">?</w>
</u>
<u n="97" who="S0034" trans="overlap" whoConfidence="high">
<w pos="CC" lemma="or" class="CONJ" usas="Z5">or</w>
<w pos="NN1" lemma="gum" class="SUBST" usas="O1:1">gum</w>
<pause dur="short"/>
<w pos="MC1" lemma="one" class="ADJ" usas="N1">one</w>
<w pos="CC" lemma="or" class="CONJ" usas="Z5">or</w>
<w pos="AT" lemma="the" class="ART" usas="Z5">the</w>
<w pos="JJ" lemma="other" class="ADJ" usas="A6:1">other</w>
<pause dur="short"/>
<w pos="RR" lemma="just" class="ADV" usas="A14">just</w>
<w pos="MC1" lemma="one" class="ADJ" usas="N1">one</w>
<w pos="IO" lemma="of" class="PREP" usas="Z5">of</w>
<w pos="AT" lemma="the" class="ART" usas="Z5">the</w>
<w pos="NN2" lemma="thing" class="SUBST" usas="O2">things</w>
<w pos="PPIS1" lemma="i" class="PRON" usas="Z8">I</w>
<w pos="VH0" lemma="have" class="VERB" usas="Z5">'ve</w>
<w pos="VVN" lemma="forget" class="VERB" usas="X2:2">forgotten</w>
<pause dur="short"/>
<w pos="VD0" lemma="do" class="VERB" usas="Z5">do</w>
<w pos="PPY" lemma="you" class="PRON" usas="Z8">you</w>
<w pos="VVI" lemma="want" class="VERB" usas="X7">want</w>
<w pos="PN1" lemma="anything" class="PRON" usas="Z8">anything</w>
<w pos="II" lemma="from" class="PREP" usas="Z5">from</w>
<w pos="RL" lemma="inside" class="ADV" usas="M6">inside</w>
<w pos="YQUE" lemma="PUNC" class="STOP" usas="">?</w>
</u>
<u n="98" who="S0109" trans="nonoverlap" whoConfidence="high">
<w pos="UH" lemma="no" class="INTERJ" usas="Z4">no</w>
<w pos="VV0" lemma="thank" class="VERB" usas="Z4">thank</w>
<w pos="PPY" lemma="you" class="PRON" usas="Z4">you</w>
<w pos="DD1" lemma="that" class="ADJ" usas="Z8">that</w>
<w pos="VBZ" lemma="be" class="VERB" usas="A3">'s</w>
<w pos="JJ" lemma="alright" class="ADJ" usas="A5:1">alright</w>
</u>
</text>
